{
  "$schema": "https://json.openmrs.org/routes.schema.json",
  "backendDependencies": {
    "fhir2": ">=1.2",
    "webservices.rest": "^2.2.0"
  },
  "extensions": [
    {
      "name": "conditions-overview-widget",
      "slot": "patient-chart-summary-dashboard-slot",
      "component": "conditionsOverview",
      "order": 3,
      "meta": {
        "fullWidth": false
      }
    },
    {
      "name": "conditions-details-widget",
      "slot": "patient-chart-conditions-dashboard-slot",
      "component": "conditionsDetailedSummary",
      "meta": {
        "fullWidth": false
      }
    },
    {
      "name": "conditions-summary-dashboard",
      "component": "conditionsDashboardLink",
      "slot": "patient-chart-dashboard-slot",
      "order": 7,
      "meta": {
        "slot": "patient-chart-conditions-dashboard-slot",
        "path": "Conditions"
      }
    },
    {
      "name": "conditions-widget",
      "component": "conditionsWidget"
    }
  ],
  "modals": [
    {
      "name": "condition-delete-confirmation-dialog",
      "component": "conditionDeleteConfirmationModal"
    }
  ],
  "workspaces": [
    {
      "name": "conditions-form-workspace",
      "title": "recordCondition",
      "component": "conditionsFormWorkspace",
      "type": "form"
    }
  ]
}
